autokeystroke/__init__.py
autokeystroke/modeling/__init__.py
autokeystroke/modeling/trainer.py
autokeystroke/utils/__init__.py
autokeystroke/utils/config.py
autokeystroke/utils/data_processing.py
autokeystroke/visuals/__init__.py
autokeystroke/visuals/base_analysis.py
autokeystroke/visuals/temporal_analysis.py
autokeystroke-0.0.9.dist-info/METADATA
autokeystroke-0.0.9.dist-info/WHEEL
autokeystroke-0.0.9.dist-info/licenses/LICENCE
autokeystroke-0.0.9.dist-info/RECORD
